<?xml version="1.0" encoding="utf-8" ?><dwsync><file name=".DS_Store" server="www.zipless.net/www/zip/wp-content/themes/2013z/" local="3457690001" remote="12047671952" /><file name="jquery.fittext.js" server="www.zipless.net/www/zip/wp-content/themes/2013z/" local="3454718428" remote="12047671952" /><file name="jquery.fitvids.js" server="www.zipless.net/www/zip/wp-content/themes/2013z/" local="3449603894" remote="12047671952" /><file name="main.js" server="www.zipless.net/www/zip/wp-content/themes/2013z/" local="3448176118" remote="12047671952" /><file name="plugins.js" server="www.zipless.net/www/zip/wp-content/themes/2013z/" local="3448176118" remote="12047671952" /><file name="jquery.fittext.js" server="ruimage.sakura.ne.jp/www/zip/wp-content/themes/2013z/" local="3457741080" remote="12049633412" /><file name="jquery.fitvids.js" server="ruimage.sakura.ne.jp/www/zip/wp-content/themes/2013z/" local="3457741080" remote="12049633412" /><file name="main.js" server="ruimage.sakura.ne.jp/www/zip/wp-content/themes/2013z/" local="3457741080" remote="12049633412" /><file name="plugins.js" server="ruimage.sakura.ne.jp/www/zip/wp-content/themes/2013z/" local="3457741080" remote="12049633412" /><file name=".DS_Store" server="ruimage.sakura.ne.jp/www/zip/wp-content/themes/2013z/" local="3457690001" remote="12049633412" /><file name="jquery.lazyload.min.js" server="ruimage.sakura.ne.jp/www/zip/wp-content/themes/2013z/" local="3459698699" remote="12049633412" /></dwsync>